filtocsv/__init__.py
filtocsv-0.3.dist-info/METADATA
filtocsv-0.3.dist-info/WHEEL
filtocsv-0.3.dist-info/top_level.txt
filtocsv-0.3.dist-info/RECORD
