Metadata-Version: 2.1
Name: filtocsv
Version: 0.3
Summary: Library to convert .FIL (List of database objects stored in a database; created by early versions of dBASE, as well as ACL for Windows) to csv for later use with pandas DataFrame.
Home-page: https://github.com/manoelgadi/fil2csv
Author: Prof. Manoel Gadi
Author-email: mfalonso@faculty.ie.edu
License: MIT
Platform: UNKNOWN
